django_toolshed/__init__.py
django_toolshed/apps.py
django_toolshed/celery_auto_app.py
django_toolshed/celery_urls.py
django_toolshed/celery_views.py
django_toolshed/management/commands/create_management_command.py
django_toolshed/management/commands/list_apps.py
django_toolshed/management/commands/list_commands.py
django_toolshed/management/commands/list_users.py
django_toolshed/mixins.py
django_toolshed/signals.py
django_toolshed/static/django_toolshed/css/.gitkeep
django_toolshed/static/django_toolshed/images/.gitkeep
django_toolshed/static/django_toolshed/js/.gitkeep
django_toolshed/templates/django_toolshed/.gitkeep
django_toolshed/urls.py
django_toolshed-0.5.9.dist-info/LICENSE
django_toolshed-0.5.9.dist-info/METADATA
django_toolshed-0.5.9.dist-info/WHEEL
django_toolshed-0.5.9.dist-info/entry_points.txt
django_toolshed-0.5.9.dist-info/RECORD
