Metadata-Version: 2.1
Name: django-toolshed
Version: 0.5.9
Summary: 
License: MIT
Author: Dani Hodovic
Author-email: you@example.com
Requires-Python: >=3.8,<4.0
Classifier: License :: OSI Approved :: MIT License
Classifier: Programming Language :: Python :: 3
Classifier: Programming Language :: Python :: 3.8
Classifier: Programming Language :: Python :: 3.9
Classifier: Programming Language :: Python :: 3.10
Classifier: Programming Language :: Python :: 3.11
Requires-Dist: celery (==5.*)
Requires-Dist: django-click (==2.*)
Requires-Dist: djangorestframework (==3.*)
Requires-Dist: drf-spectacular (==0.*)
Requires-Dist: iterfzf (>=0.5.0,<0.6.0)
